advanced_data_generator-1.0.0.dist-info/licenses/LICENSE
utils/__init__.py
utils/config.py
utils/validator.py
advanced_data_generator-1.0.0.dist-info/METADATA
advanced_data_generator-1.0.0.dist-info/WHEEL
advanced_data_generator-1.0.0.dist-info/entry_points.txt
advanced_data_generator-1.0.0.dist-info/top_level.txt
advanced_data_generator-1.0.0.dist-info/RECORD
