Metadata-Version: 2.4
Name: advanced-data-generator
Version: 1.0.0
Summary: Advanced Data Generator - A powerful tool for generating realistic test data
Home-page: https://github.com/ilyanozary/advanced-data-generator
Author: ilyanozary
Author-email: ilyanozary.dynamic@gmail.com
Classifier: Programming Language :: Python :: 3
Classifier: License :: OSI Approved :: MIT License
Classifier: Operating System :: OS Independent
Requires-Python: >=3.8
License-File: LICENSE
Requires-Dist: faker==19.13.0
Requires-Dist: sqlalchemy==2.0.25
Requires-Dist: pandas==2.1.4
Requires-Dist: streamlit==1.29.0
Requires-Dist: plotly==5.18.0
Requires-Dist: pyyaml==6.0.1
Requires-Dist: python-dateutil==2.8.2
Requires-Dist: pytest>=7.4.0
Requires-Dist: black>=23.7.0
Requires-Dist: flake8>=6.1.0
Requires-Dist: python-dotenv>=1.0.0
Dynamic: author
Dynamic: author-email
Dynamic: classifier
Dynamic: description
Dynamic: description-content-type
Dynamic: home-page
Dynamic: license-file
Dynamic: requires-dist
Dynamic: requires-python
Dynamic: summary
